yarll/__init__.py
yarll/main.py
yarll/actionselection/__init__.py
yarll/actionselection/action_selection.py
yarll/actionselection/categorical_action_selection.py
yarll/actionselection/continuous_action_selection.py
yarll/agents/__init__.py
yarll/agents/agent.py
yarll/agents/cem.py
yarll/agents/ddpg.py
yarll/agents/env_runner.py
yarll/agents/karpathy.py
yarll/agents/karpathy_cnn.py
yarll/agents/registration.py
yarll/agents/reinforce.py
yarll/agents/sac.py
yarll/agents/actorcritic/__init__.py
yarll/agents/actorcritic/a2c.py
yarll/agents/actorcritic/a3c.py
yarll/agents/actorcritic/a3c_worker.py
yarll/agents/actorcritic/actor_critic.py
yarll/agents/actorcritic/attention.py
yarll/agents/actorcritic/parameter_server.py
yarll/agents/knowledgetransfer/__init__.py
yarll/agents/knowledgetransfer/async_knowledge_transfer.py
yarll/agents/knowledgetransfer/knowledge_transfer.py
yarll/agents/ppo/__init__.py
yarll/agents/ppo/dppo.py
yarll/agents/ppo/dppo_worker.py
yarll/agents/ppo/ppo.py
yarll/agents/sarsa/__init__.py
yarll/agents/sarsa/sarsa.py
yarll/agents/sarsa/sarsa_fa.py
yarll/agents/trpo/__init__.py
yarll/agents/trpo/dtrpo.py
yarll/agents/trpo/trpo.py
yarll/environment/__init__.py
yarll/environment/acrobot.py
yarll/environment/cartpole.py
yarll/environment/environment.py
yarll/environment/registration.py
yarll/environment/wrappers.py
yarll/functionapproximation/__init__.py
yarll/functionapproximation/function_approximator.py
yarll/functionapproximation/tile_coding.py
yarll/memory/__init__.py
yarll/memory/experiences_memory.py
yarll/memory/memory.py
yarll/misc/__init__.py
yarll/misc/envs_statistics.py
yarll/misc/exceptions.py
yarll/misc/network_ops.py
yarll/misc/noise.py
yarll/misc/plot_statistics.py
yarll/misc/reporter.py
yarll/misc/utils.py
yarll/policies/__init__.py
yarll/policies/e_greedy.py
yarll/policies/policy.py
yarll/scripts/__init__.py
yarll/scripts/gen_envs.py
yarll/scripts/list_exps.py
yarll/scripts/run_model.py
yarll/traces/__init__.py
yarll-0.0.12.dist-info/LICENSE
yarll-0.0.12.dist-info/METADATA
yarll-0.0.12.dist-info/WHEEL
yarll-0.0.12.dist-info/top_level.txt
yarll-0.0.12.dist-info/RECORD
