Metadata-Version: 2.1
Name: yarll
Version: 0.0.12
Summary: Yet Another Reinforcement Learning Library
Home-page: https://github.com/arnomoonens/YARLL
Author: Arno Moonens
Author-email: arno.moonens@outlook.com
License: MIT
Keywords: deep learning reinforcement learning a3c ddpg sac ppo machine neural networks
Platform: UNKNOWN
Classifier: Intended Audience :: Developers
Classifier: Intended Audience :: Science/Research
Classifier: Programming Language :: Python :: 3
Classifier: License :: OSI Approved :: MIT License
Classifier: Operating System :: OS Independent
Classifier: Topic :: Scientific/Engineering
Classifier: Topic :: Scientific/Engineering :: Artificial Intelligence
Classifier: Topic :: Software Development :: Libraries :: Python Modules
Requires-Python: >=3.4
Requires-Dist: numpy
Requires-Dist: gym (>=0.8.0)
Requires-Dist: tensorflow (>=1.6.0)
Requires-Dist: matplotlib
Requires-Dist: scipy
Requires-Dist: opencv-contrib-python
